orcbench/__init__.py
orcbench/__main__.py
orcbench/internals/__init__.py
orcbench/internals/epmeans.py
orcbench/internals/orcglobals.py
orcbench/internals/run.py
orcbench/internals/stats.py
orcbench/models/0-model
orcbench/models/1-model
orcbench/models/10-model
orcbench/models/11-model
orcbench/models/12-model
orcbench/models/13-model
orcbench/models/14-model
orcbench/models/15-model
orcbench/models/16-model
orcbench/models/17-model
orcbench/models/18-model
orcbench/models/19-model
orcbench/models/2-model
orcbench/models/20-model
orcbench/models/21-model
orcbench/models/22-model
orcbench/models/23-model
orcbench/models/24-model
orcbench/models/3-model
orcbench/models/4-model
orcbench/models/5-model
orcbench/models/6-model
orcbench/models/7-model
orcbench/models/8-model
orcbench/models/9-model
orcbench/models.py
orcbench-0.1.4.dist-info/entry_points.txt
orcbench-0.1.4.dist-info/LICENSE
orcbench-0.1.4.dist-info/WHEEL
orcbench-0.1.4.dist-info/METADATA
orcbench-0.1.4.dist-info/RECORD
