Metadata-Version: 2.1
Name: orcbench
Version: 0.1.4
Summary: OrcBench: A Representative Serverless Benchmark
Author: Ryan Hancock
Author-email: krhancoc@uwaterloo.ca
Maintainer: Ryan Hancock
Maintainer-email: krhancoc@uwaterloo.ca
Requires-Python: >=3.8,<4.0
Classifier: Programming Language :: Python :: 3
Classifier: Programming Language :: Python :: 3.8
Classifier: Programming Language :: Python :: 3.9
Classifier: Programming Language :: Python :: 3.10
Classifier: Programming Language :: Python :: 3.11
Requires-Dist: click (>=8.1.3,<9.0.0)
Requires-Dist: numpy (>=1.23.1,<2.0.0)
